README.md
setup.py
Auto2DSelect/__init__.py
Auto2DSelect/augmentation.py
Auto2DSelect/auto_2d_select.py
Auto2DSelect/helper.py
Auto2DSelect/predict.py
Auto2DSelect/results_writer.py
Auto2DSelect/train.py
cinderella.egg-info/PKG-INFO
cinderella.egg-info/SOURCES.txt
cinderella.egg-info/dependency_links.txt
cinderella.egg-info/entry_points.txt
cinderella.egg-info/requires.txt
cinderella.egg-info/top_level.txt