Metadata-Version: 2.1
Name: cinderella
Version: 0.3.0
Summary: Select 2d classes automatically
Home-page: https://github.com/MPI-Dortmund/sphire_classes_autoselect
Author: Thorsten Wagner
Author-email: thorsten.wagner@mpi-dortmund.mpg.de
License: MIT
Platform: UNKNOWN
Requires-Python: >3.4.0
Provides-Extra: cpu
Provides-Extra: gpu
